refine_user_story_mcp/__init__.py
refine_user_story_mcp/analyzer.py
refine_user_story_mcp/server.py
refine_user_story_mcp-0.4.0.dist-info/licenses/LICENSE
refine_user_story_mcp-0.4.0.dist-info/METADATA
refine_user_story_mcp-0.4.0.dist-info/WHEEL
refine_user_story_mcp-0.4.0.dist-info/entry_points.txt
refine_user_story_mcp-0.4.0.dist-info/top_level.txt
refine_user_story_mcp-0.4.0.dist-info/RECORD
